{
  "url": "https://www.facebook.com/tr?id=674478425975295&ev=PageView&dl=https%3A%2F%2Fwww.airbnb.fr%2Flogin%3Fredirect_url%3D%252Fmulticalendar%252F&rl=&eid=undefined&ud[external_id]=1772798434_EAZjYyODY2YzY2OW&fbc=undefined&ud[em]=&ud[ph]=&ud[fn]=&ud[ln]=&ud[db]=&ud[ge]=&ud[ct]=&ud[st]=&ud[cn]=&dpo=&noscript=1&gtmcb=643536960",
  "method": "GET",
  "status": 200,
  "headers": {
    "strict-transport-security": "max-age=31536000; includeSubDomains",
    "x-fb-connection-quality": "EXCELLENT; q=0.9, rtt=20, rtx=0, c=23, mss=1232, tbw=5219, tp=9, tpl=0, uplat=0, ullat=0",
    "cross-origin-resource-policy": "cross-origin",
    "access-control-allow-credentials": "true",
    "access-control-allow-origin": "",
    "alt-svc": "h3=\":443\"; ma=86400",
    "content-length": "0",
    "date": "Fri, 06 Mar 2026 12:00:40 GMT",
    "content-type": "text/plain",
    "server": "proxygen-bolt",
    "priority": "u=3,i"
  },
  "requestHeaders": {
    "sec-ch-ua-platform": "\"macOS\"",
    "referer": "https://www.airbnb.fr/",
    "user-agent": "Mozilla/5.0 (Macintosh; Intel Mac OS X 10_15_7) AppleWebKit/537.36 (KHTML, like Gecko) Chrome/145.0.0.0 Safari/537.36",
    "sec-ch-ua": "\"Chromium\";v=\"145\", \"Not:A-Brand\";v=\"99\"",
    "sec-ch-ua-mobile": "?0"
  },
  "contentType": "text/plain",
  "body": "",
  "timestamp": "2026-03-06T12:00:40.550Z",
  "context": "login",
  "filterExplanation": "No filters applied, keeping all responses"
}